pythymiodw/__init__.py
pythymiodw/killasebamedulla.py
pythymiodw/thymiohandlers.aesl
pythymiodw/images/iodisplay.png
pythymiodw/io/__init__.py
pythymiodw/pg/__init__.py
pythymiodw/pg/images/thymio1.png
pythymiodw/pg/images/thymio2.png
pythymiodw/pg/images/thymio3.png
pythymiodw/pg/images/thymio4.png
pythymiodw/pg/images/thymio5.png
pythymiodw/pyro/__init__.py
pythymiodw/pyro/__main__.py
pythymiodw/sm/__init__.py
pythymiodw/world/__init__.py
pythymiodw-2.4.1.dist-info/LICENSE.txt
pythymiodw-2.4.1.dist-info/METADATA
pythymiodw-2.4.1.dist-info/WHEEL
pythymiodw-2.4.1.dist-info/top_level.txt
pythymiodw-2.4.1.dist-info/RECORD
