Metadata-Version: 2.1
Name: pythymiodw
Version: 2.4.1
Summary: Python library for Thymio used in Digital World class
Home-page: https://github.com/kurniawano/pythymiodw
Author: Oka Kurniawan
Author-email: kurniawano@ieee.org
License: MIT
Keywords: robot library education
Platform: UNKNOWN
Classifier: Development Status :: 4 - Beta
Classifier: Intended Audience :: Education
Classifier: License :: OSI Approved :: MIT License
Classifier: Operating System :: POSIX :: Linux
Classifier: Programming Language :: Python :: 3
Classifier: Topic :: Education
Requires-Dist: libdw
Requires-Dist: pygame
Requires-Dist: requests
Requires-Dist: Pyro4
Requires-Dist: cryptography
